{
    "metadata": {
        "provider": "Oxford University Press",
        "limit": 5000,
        "sourceLanguage": "en",
        "total": 81,
        "offset": 0
    },
    "results": [
        {
            "id": "aaa",
            "word": "aaa"
        },
        {
            "id": "aau",
            "word": "aau"
        },
        {
            "id": "abrahams%2C_harold",
            "word": "abrahams, harold"
        },
        {
            "id": "athletics",
            "word": "athletics"
        },
        {
            "id": "bannister%2C_sir_roger",
            "word": "bannister, sir roger"
        },
        {
            "id": "barefoot_runner",
            "word": "barefoot runner"
        },
        {
            "id": "barefoot_running",
            "word": "barefoot running"
        },
        {
            "id": "beamon%2C_bob",
            "word": "beamon, bob"
        },
        {
            "id": "blood_doping",
            "word": "blood doping"
        },
        {
            "id": "bolt%2C_usain",
            "word": "bolt, usain"
        },
        {
            "id": "christie%2C_linford",
            "word": "christie, linford"
        },
        {
            "id": "circuit",
            "word": "circuit"
        },
        {
            "id": "coe%2C_sebastian",
            "word": "coe, sebastian"
        },
        {
            "id": "decathlete",
            "word": "decathlete"
        },
        {
            "id": "distance_runner",
            "word": "distance runner"
        },
        {
            "id": "edwards%2C_jonathan",
            "word": "edwards, jonathan"
        },
        {
            "id": "ennis-hill%2C_jessica",
            "word": "ennis-hill, jessica"
        },
        {
            "id": "farah%2C_sir_mo",
            "word": "farah, sir mo"
        },
        {
            "id": "fartlek",
            "word": "fartlek"
        },
        {
            "id": "field_events",
            "word": "field events"
        },
        {
            "id": "finishing_post",
            "word": "finishing post"
        },
        {
            "id": "fosbury%2C_dick",
            "word": "fosbury, dick"
        },
        {
            "id": "freeman%2C_cathy",
            "word": "freeman, cathy"
        },
        {
            "id": "front_runner",
            "word": "front runner"
        },
        {
            "id": "gunnell%2C_sally",
            "word": "gunnell, sally"
        },
        {
            "id": "half-marathon",
            "word": "half-marathon"
        },
        {
            "id": "heptathlete",
            "word": "heptathlete"
        },
        {
            "id": "heptathlon",
            "word": "heptathlon"
        },
        {
            "id": "high-intensity_interval_training",
            "word": "high-intensity interval training"
        },
        {
            "id": "high_jump",
            "word": "high jump"
        },
        {
            "id": "hiit",
            "word": "hiit"
        },
        {
            "id": "holmes%2C_dame_kelly",
            "word": "holmes, dame kelly"
        },
        {
            "id": "hurdle",
            "word": "hurdle"
        },
        {
            "id": "hurdling",
            "word": "hurdling"
        },
        {
            "id": "iaaf",
            "word": "iaaf"
        },
        {
            "id": "interval",
            "word": "interval"
        },
        {
            "id": "interval_training",
            "word": "interval training"
        },
        {
            "id": "isthmian_games",
            "word": "isthmian games"
        },
        {
            "id": "javelin",
            "word": "javelin"
        },
        {
            "id": "javelin_thrower",
            "word": "javelin thrower"
        },
        {
            "id": "javelin_throwing",
            "word": "javelin throwing"
        },
        {
            "id": "jogging",
            "word": "jogging"
        },
        {
            "id": "johnson%2C_michael",
            "word": "johnson, michael"
        },
        {
            "id": "lewis%2C_carl",
            "word": "lewis, carl"
        },
        {
            "id": "liddell%2C_eric",
            "word": "liddell, eric"
        },
        {
            "id": "long_jump",
            "word": "long jump"
        },
        {
            "id": "marathon",
            "word": "marathon"
        },
        {
            "id": "metric_mile",
            "word": "metric mile"
        },
        {
            "id": "miler",
            "word": "miler"
        },
        {
            "id": "moses%2C_edwin",
            "word": "moses, edwin"
        },
        {
            "id": "outjump",
            "word": "outjump"
        },
        {
            "id": "owens%2C_jesse",
            "word": "owens, jesse"
        },
        {
            "id": "pacemaker",
            "word": "pacemaker"
        },
        {
            "id": "pacer",
            "word": "pacer"
        },
        {
            "id": "paralympian",
            "word": "paralympian"
        },
        {
            "id": "pentathlete",
            "word": "pentathlete"
        },
        {
            "id": "pole",
            "word": "pole"
        },
        {
            "id": "pole_vault",
            "word": "pole vault"
        },
        {
            "id": "racetrack",
            "word": "racetrack"
        },
        {
            "id": "radcliffe%2C_paula",
            "word": "radcliffe, paula"
        },
        {
            "id": "ringer",
            "word": "ringer"
        },
        {
            "id": "ring-in",
            "word": "ring-in"
        },
        {
            "id": "runner",
            "word": "runner"
        },
        {
            "id": "running",
            "word": "running"
        },
        {
            "id": "scissors",
            "word": "scissors"
        },
        {
            "id": "shot-put",
            "word": "shot-put"
        },
        {
            "id": "sprinter",
            "word": "sprinter"
        },
        {
            "id": "starting_post",
            "word": "starting post"
        },
        {
            "id": "take_up_the_running",
            "word": "take up the running"
        },
        {
            "id": "thompson%2C_daley",
            "word": "thompson, daley"
        },
        {
            "id": "track",
            "word": "track"
        },
        {
            "id": "track_events",
            "word": "track events"
        },
        {
            "id": "track_shoe",
            "word": "track shoe"
        },
        {
            "id": "tracksuit",
            "word": "tracksuit"
        },
        {
            "id": "triple_jump",
            "word": "triple jump"
        },
        {
            "id": "ultramarathon",
            "word": "ultramarathon"
        },
        {
            "id": "ultrarunning",
            "word": "ultrarunning"
        },
        {
            "id": "walker%2C_john",
            "word": "walker, john"
        },
        {
            "id": "wind_sprint",
            "word": "wind sprint"
        },
        {
            "id": "winning_post",
            "word": "winning post"
        },
        {
            "id": "zatopek%2C_emil",
            "word": "zatopek, emil"
        }
    ]
}
