{
    "results": [
        {
            "id": "arabesque",
            "word": "arabesque"
        },
        {
            "id": "ashton%2C_sir_frederick",
            "word": "ashton, sir frederick"
        },
        {
            "id": "assembl%C3%A9",
            "word": "assemblé"
        },
        {
            "id": "balanchine%2C_george",
            "word": "balanchine, george"
        },
        {
            "id": "ballerina",
            "word": "ballerina"
        },
        {
            "id": "ballerino",
            "word": "ballerino"
        },
        {
            "id": "ballet",
            "word": "ballet"
        },
        {
            "id": "ballet_dancer",
            "word": "ballet dancer"
        },
        {
            "id": "ballet_master",
            "word": "ballet master"
        },
        {
            "id": "balletomane",
            "word": "balletomane"
        },
        {
            "id": "ballets_russes",
            "word": "ballets russes"
        },
        {
            "id": "ballon",
            "word": "ballon"
        },
        {
            "id": "ballonn%C3%A9",
            "word": "ballonné"
        },
        {
            "id": "ballott%C3%A9",
            "word": "ballotté"
        },
        {
            "id": "baryshnikov%2C_mikhail",
            "word": "baryshnikov, mikhail"
        },
        {
            "id": "battement",
            "word": "battement"
        },
        {
            "id": "batterie",
            "word": "batterie"
        },
        {
            "id": "b%C3%A9jart%2C_maurice",
            "word": "béjart, maurice"
        },
        {
            "id": "bolshoi_ballet",
            "word": "bolshoi ballet"
        },
        {
            "id": "bris%C3%A9",
            "word": "brisé"
        },
        {
            "id": "%C3%A9chapp%C3%A9",
            "word": "échappé"
        },
        {
            "id": "cabriole",
            "word": "cabriole"
        },
        {
            "id": "cha%C3%AEn%C3%A9",
            "word": "chaîné"
        },
        {
            "id": "changement_de_pieds",
            "word": "changement de pieds"
        },
        {
            "id": "character_dance",
            "word": "character dance"
        },
        {
            "id": "chass%C3%A9",
            "word": "chassé"
        },
        {
            "id": "corps_de_ballet",
            "word": "corps de ballet"
        },
        {
            "id": "coryph%C3%A9e",
            "word": "coryphée"
        },
        {
            "id": "cunningham%2C_merce",
            "word": "cunningham, merce"
        },
        {
            "id": "danseur",
            "word": "danseur"
        },
        {
            "id": "danseur_noble",
            "word": "danseur noble"
        },
        {
            "id": "danseuse",
            "word": "danseuse"
        },
        {
            "id": "d%C3%A9velopp%C3%A9",
            "word": "développé"
        },
        {
            "id": "demi-caract%C3%A8re",
            "word": "demi-caractère"
        },
        {
            "id": "de_valois%2C_dame_ninette",
            "word": "de valois, dame ninette"
        },
        {
            "id": "diaghilev%2C_sergei",
            "word": "diaghilev, sergei"
        },
        {
            "id": "divertissement",
            "word": "divertissement"
        },
        {
            "id": "dolin%2C_sir_anton",
            "word": "dolin, sir anton"
        },
        {
            "id": "duncan%2C_isadora",
            "word": "duncan, isadora"
        },
        {
            "id": "encha%C3%AEnement",
            "word": "enchaînement"
        },
        {
            "id": "entrechat",
            "word": "entrechat"
        },
        {
            "id": "fifth_position",
            "word": "fifth position"
        },
        {
            "id": "first_position",
            "word": "first position"
        },
        {
            "id": "fokine%2C_michel",
            "word": "fokine, michel"
        },
        {
            "id": "fondu",
            "word": "fondu"
        },
        {
            "id": "fonteyn%2C_dame_margot",
            "word": "fonteyn, dame margot"
        },
        {
            "id": "footwork",
            "word": "footwork"
        },
        {
            "id": "fouett%C3%A9",
            "word": "fouetté"
        },
        {
            "id": "fourth_position",
            "word": "fourth position"
        },
        {
            "id": "frapp%C3%A9",
            "word": "frappé"
        },
        {
            "id": "gliss%C3%A9",
            "word": "glissé"
        },
        {
            "id": "graham%2C_martha",
            "word": "graham, martha"
        },
        {
            "id": "grand_battement",
            "word": "grand battement"
        },
        {
            "id": "grand_jet%C3%A9",
            "word": "grand jeté"
        },
        {
            "id": "helpmann%2C_sir_robert",
            "word": "helpmann, sir robert"
        },
        {
            "id": "jet%C3%A9",
            "word": "jeté"
        },
        {
            "id": "jet%C3%A9_en_tournant",
            "word": "jeté en tournant"
        },
        {
            "id": "laban%2C_rudolf_von",
            "word": "laban, rudolf von"
        },
        {
            "id": "markova%2C_dame_alicia",
            "word": "markova, dame alicia"
        },
        {
            "id": "massine%2C_l%C3%A9onide",
            "word": "massine, léonide"
        },
        {
            "id": "nijinsky%2C_vaslav",
            "word": "nijinsky, vaslav"
        },
        {
            "id": "noverre%2C_jean-georges",
            "word": "noverre, jean-georges"
        },
        {
            "id": "nureyev%2C_rudolf",
            "word": "nureyev, rudolf"
        },
        {
            "id": "ouvert",
            "word": "ouvert"
        },
        {
            "id": "pas",
            "word": "pas"
        },
        {
            "id": "pas_d%27action",
            "word": "pas d'action"
        },
        {
            "id": "pas_de_basque",
            "word": "pas de basque"
        },
        {
            "id": "pas_de_bourr%C3%A9e",
            "word": "pas de bourrée"
        },
        {
            "id": "pas_de_chat",
            "word": "pas de chat"
        },
        {
            "id": "pas_de_cheval",
            "word": "pas de cheval"
        },
        {
            "id": "pas_seul",
            "word": "pas seul"
        },
        {
            "id": "pavlova%2C_anna",
            "word": "pavlova, anna"
        },
        {
            "id": "pench%C3%A9e",
            "word": "penchée"
        },
        {
            "id": "petipa%2C_marius",
            "word": "petipa, marius"
        },
        {
            "id": "petit_battement",
            "word": "petit battement"
        },
        {
            "id": "petit_jet%C3%A9",
            "word": "petit jeté"
        },
        {
            "id": "pirouette",
            "word": "pirouette"
        },
        {
            "id": "pli%C3%A9",
            "word": "plié"
        },
        {
            "id": "pointe",
            "word": "pointe"
        },
        {
            "id": "pointe_shoe",
            "word": "pointe shoe"
        },
        {
            "id": "pointwork",
            "word": "pointwork"
        },
        {
            "id": "port_de_bras",
            "word": "port de bras"
        },
        {
            "id": "porteur",
            "word": "porteur"
        },
        {
            "id": "prima_ballerina",
            "word": "prima ballerina"
        },
        {
            "id": "primo_ballerino",
            "word": "primo ballerino"
        },
        {
            "id": "rambert%2C_dame_marie",
            "word": "rambert, dame marie"
        },
        {
            "id": "r%C3%A9p%C3%A9titeur",
            "word": "répétiteur"
        },
        {
            "id": "regisseur",
            "word": "regisseur"
        },
        {
            "id": "relev%C3%A9",
            "word": "relevé"
        },
        {
            "id": "retir%C3%A9",
            "word": "retiré"
        },
        {
            "id": "robbins%2C_jerome",
            "word": "robbins, jerome"
        },
        {
            "id": "rond_de_jambe",
            "word": "rond de jambe"
        },
        {
            "id": "royal_ballet",
            "word": "royal ballet"
        },
        {
            "id": "russian_ballet",
            "word": "russian ballet"
        },
        {
            "id": "second_position",
            "word": "second position"
        },
        {
            "id": "seymour%2C_lynn",
            "word": "seymour, lynn"
        },
        {
            "id": "shankar%2C_uday",
            "word": "shankar, uday"
        },
        {
            "id": "shearer%2C_moira",
            "word": "shearer, moira"
        },
        {
            "id": "soubresaut",
            "word": "soubresaut"
        },
        {
            "id": "temps_lev%C3%A9",
            "word": "temps levé"
        },
        {
            "id": "tendu",
            "word": "tendu"
        },
        {
            "id": "third_position",
            "word": "third position"
        },
        {
            "id": "tour_en_l%27air",
            "word": "tour en l'air"
        },
        {
            "id": "tutu",
            "word": "tutu"
        },
        {
            "id": "ulanova%2C_galina",
            "word": "ulanova, galina"
        },
        {
            "id": "vic-wells_ballet",
            "word": "vic-wells ballet"
        }
    ],
    "metadata": {
        "limit": 5000,
        "sourceLanguage": "en",
        "total": 106,
        "provider": "Oxford University Press",
        "offset": 0
    }
}
