{
    "results": [
        {
            "id": "abbacy",
            "word": "abbacy"
        },
        {
            "id": "abbatial",
            "word": "abbatial"
        },
        {
            "id": "abbess",
            "word": "abbess"
        },
        {
            "id": "abbey",
            "word": "abbey"
        },
        {
            "id": "abbot",
            "word": "abbot"
        },
        {
            "id": "abp",
            "word": "abp"
        },
        {
            "id": "advowson",
            "word": "advowson"
        },
        {
            "id": "amice",
            "word": "amice"
        },
        {
            "id": "antidisestablishmentarianism",
            "word": "antidisestablishmentarianism"
        },
        {
            "id": "archbishopric",
            "word": "archbishopric"
        },
        {
            "id": "archdeacon",
            "word": "archdeacon"
        },
        {
            "id": "archdeaconry",
            "word": "archdeaconry"
        },
        {
            "id": "archdiocese",
            "word": "archdiocese"
        },
        {
            "id": "archidiaconal",
            "word": "archidiaconal"
        },
        {
            "id": "archiepiscopal",
            "word": "archiepiscopal"
        },
        {
            "id": "autocephalous",
            "word": "autocephalous"
        },
        {
            "id": "beadle",
            "word": "beadle"
        },
        {
            "id": "beguinage",
            "word": "beguinage"
        },
        {
            "id": "benefice",
            "word": "benefice"
        },
        {
            "id": "benefit_of_clergy",
            "word": "benefit of clergy"
        },
        {
            "id": "bishopric",
            "word": "bishopric"
        },
        {
            "id": "bush_brother",
            "word": "bush brother"
        },
        {
            "id": "canon",
            "word": "canon"
        },
        {
            "id": "canoness",
            "word": "canoness"
        },
        {
            "id": "canonical",
            "word": "canonical"
        },
        {
            "id": "canonical_hours",
            "word": "canonical hours"
        },
        {
            "id": "canonicity",
            "word": "canonicity"
        },
        {
            "id": "canonist",
            "word": "canonist"
        },
        {
            "id": "canonize",
            "word": "canonize"
        },
        {
            "id": "canon_law",
            "word": "canon law"
        },
        {
            "id": "canonry",
            "word": "canonry"
        },
        {
            "id": "canterbury%2C_archbishop_of",
            "word": "canterbury, archbishop of"
        },
        {
            "id": "cantorial",
            "word": "cantorial"
        },
        {
            "id": "capitular",
            "word": "capitular"
        },
        {
            "id": "cassock",
            "word": "cassock"
        },
        {
            "id": "chantry",
            "word": "chantry"
        },
        {
            "id": "chapelry",
            "word": "chapelry"
        },
        {
            "id": "chaplaincy",
            "word": "chaplaincy"
        },
        {
            "id": "chapter_house",
            "word": "chapter house"
        },
        {
            "id": "choir_school",
            "word": "choir school"
        },
        {
            "id": "chrisom",
            "word": "chrisom"
        },
        {
            "id": "church_commissioners",
            "word": "church commissioners"
        },
        {
            "id": "churchwarden",
            "word": "churchwarden"
        },
        {
            "id": "ciborium",
            "word": "ciborium"
        },
        {
            "id": "circuit_rider",
            "word": "circuit rider"
        },
        {
            "id": "claustral",
            "word": "claustral"
        },
        {
            "id": "clergy",
            "word": "clergy"
        },
        {
            "id": "clergyman",
            "word": "clergyman"
        },
        {
            "id": "clergywoman",
            "word": "clergywoman"
        },
        {
            "id": "clerical_collar",
            "word": "clerical collar"
        },
        {
            "id": "clerk_of_the_closet",
            "word": "clerk of the closet"
        },
        {
            "id": "coadjutor",
            "word": "coadjutor"
        },
        {
            "id": "collect",
            "word": "collect"
        },
        {
            "id": "collegiate_church",
            "word": "collegiate church"
        },
        {
            "id": "compline",
            "word": "compline"
        },
        {
            "id": "conventual",
            "word": "conventual"
        },
        {
            "id": "convocation",
            "word": "convocation"
        },
        {
            "id": "cope",
            "word": "cope"
        },
        {
            "id": "cordelier",
            "word": "cordelier"
        },
        {
            "id": "corporal",
            "word": "corporal"
        },
        {
            "id": "cotta",
            "word": "cotta"
        },
        {
            "id": "crockford",
            "word": "crockford"
        },
        {
            "id": "crook",
            "word": "crook"
        },
        {
            "id": "crozier",
            "word": "crozier"
        },
        {
            "id": "crutched_friars",
            "word": "crutched friars"
        },
        {
            "id": "curacy",
            "word": "curacy"
        },
        {
            "id": "curate",
            "word": "curate"
        },
        {
            "id": "cur%C3%A9",
            "word": "curé"
        },
        {
            "id": "dalmatic",
            "word": "dalmatic"
        },
        {
            "id": "dd",
            "word": "dd"
        },
        {
            "id": "deacon",
            "word": "deacon"
        },
        {
            "id": "deanery",
            "word": "deanery"
        },
        {
            "id": "decanal",
            "word": "decanal"
        },
        {
            "id": "deconsecrate",
            "word": "deconsecrate"
        },
        {
            "id": "decretal",
            "word": "decretal"
        },
        {
            "id": "decretum",
            "word": "decretum"
        },
        {
            "id": "defrock",
            "word": "defrock"
        },
        {
            "id": "diaconate",
            "word": "diaconate"
        },
        {
            "id": "dimissory",
            "word": "dimissory"
        },
        {
            "id": "diocesan",
            "word": "diocesan"
        },
        {
            "id": "diocese",
            "word": "diocese"
        },
        {
            "id": "dirge",
            "word": "dirge"
        },
        {
            "id": "diriment_impediment",
            "word": "diriment impediment"
        },
        {
            "id": "dominical_letter",
            "word": "dominical letter"
        },
        {
            "id": "dossal",
            "word": "dossal"
        },
        {
            "id": "doxology",
            "word": "doxology"
        },
        {
            "id": "ecclesial",
            "word": "ecclesial"
        },
        {
            "id": "ecclesiarch",
            "word": "ecclesiarch"
        },
        {
            "id": "ecclesiastic",
            "word": "ecclesiastic"
        },
        {
            "id": "ecclesiastical",
            "word": "ecclesiastical"
        },
        {
            "id": "ecumenical",
            "word": "ecumenical"
        },
        {
            "id": "ecumenism",
            "word": "ecumenism"
        },
        {
            "id": "elevate",
            "word": "elevate"
        },
        {
            "id": "eparch",
            "word": "eparch"
        },
        {
            "id": "eparchy",
            "word": "eparchy"
        },
        {
            "id": "episcopacy",
            "word": "episcopacy"
        },
        {
            "id": "episcopal",
            "word": "episcopal"
        },
        {
            "id": "episcopalian",
            "word": "episcopalian"
        },
        {
            "id": "episcopate",
            "word": "episcopate"
        },
        {
            "id": "erastian",
            "word": "erastian"
        },
        {
            "id": "erastianism",
            "word": "erastianism"
        },
        {
            "id": "establishmentarian",
            "word": "establishmentarian"
        },
        {
            "id": "evangel",
            "word": "evangel"
        },
        {
            "id": "exarch",
            "word": "exarch"
        },
        {
            "id": "excommunicant",
            "word": "excommunicant"
        },
        {
            "id": "excommunicate",
            "word": "excommunicate"
        },
        {
            "id": "excommunication",
            "word": "excommunication"
        },
        {
            "id": "excommunicator",
            "word": "excommunicator"
        },
        {
            "id": "exequy",
            "word": "exequy"
        },
        {
            "id": "extreme_unction",
            "word": "extreme unction"
        },
        {
            "id": "faldstool",
            "word": "faldstool"
        },
        {
            "id": "familia",
            "word": "familia"
        },
        {
            "id": "first_communion",
            "word": "first communion"
        },
        {
            "id": "formulary",
            "word": "formulary"
        },
        {
            "id": "fr",
            "word": "fr"
        },
        {
            "id": "fra",
            "word": "fra"
        },
        {
            "id": "frater",
            "word": "frater"
        },
        {
            "id": "frontal",
            "word": "frontal"
        },
        {
            "id": "frontlet",
            "word": "frontlet"
        },
        {
            "id": "general_synod",
            "word": "general synod"
        },
        {
            "id": "general_thanksgiving",
            "word": "general thanksgiving"
        },
        {
            "id": "geneva_bands",
            "word": "geneva bands"
        },
        {
            "id": "genuflect",
            "word": "genuflect"
        },
        {
            "id": "glebe",
            "word": "glebe"
        },
        {
            "id": "glebe_house",
            "word": "glebe house"
        },
        {
            "id": "gloria",
            "word": "gloria"
        },
        {
            "id": "hassock",
            "word": "hassock"
        },
        {
            "id": "hocktide",
            "word": "hocktide"
        },
        {
            "id": "holy_orders",
            "word": "holy orders"
        },
        {
            "id": "homiletic",
            "word": "homiletic"
        },
        {
            "id": "homiliary",
            "word": "homiliary"
        },
        {
            "id": "homily",
            "word": "homily"
        },
        {
            "id": "hospitaller",
            "word": "hospitaller"
        },
        {
            "id": "host",
            "word": "host"
        },
        {
            "id": "hymnal",
            "word": "hymnal"
        },
        {
            "id": "hymnody",
            "word": "hymnody"
        },
        {
            "id": "hymnographer",
            "word": "hymnographer"
        },
        {
            "id": "hymnology",
            "word": "hymnology"
        },
        {
            "id": "impropriate",
            "word": "impropriate"
        },
        {
            "id": "impropriator",
            "word": "impropriator"
        },
        {
            "id": "incense",
            "word": "incense"
        },
        {
            "id": "incense_burner",
            "word": "incense burner"
        },
        {
            "id": "induct",
            "word": "induct"
        },
        {
            "id": "infula",
            "word": "infula"
        },
        {
            "id": "in_the_gift_of",
            "word": "in the gift of"
        },
        {
            "id": "intinction",
            "word": "intinction"
        },
        {
            "id": "introit",
            "word": "introit"
        },
        {
            "id": "itinerate",
            "word": "itinerate"
        },
        {
            "id": "kirk_session",
            "word": "kirk session"
        },
        {
            "id": "kyrie",
            "word": "kyrie"
        },
        {
            "id": "lady_superior",
            "word": "lady superior"
        },
        {
            "id": "laicize",
            "word": "laicize"
        },
        {
            "id": "lambeth_palace",
            "word": "lambeth palace"
        },
        {
            "id": "last_rites",
            "word": "last rites"
        },
        {
            "id": "lateran_council",
            "word": "lateran council"
        },
        {
            "id": "lauds",
            "word": "lauds"
        },
        {
            "id": "lay",
            "word": "lay"
        },
        {
            "id": "layman",
            "word": "layman"
        },
        {
            "id": "layperson",
            "word": "layperson"
        },
        {
            "id": "lay_reader",
            "word": "lay reader"
        },
        {
            "id": "laywoman",
            "word": "laywoman"
        },
        {
            "id": "lectionary",
            "word": "lectionary"
        },
        {
            "id": "lector",
            "word": "lector"
        },
        {
            "id": "letter_missive",
            "word": "letter missive"
        },
        {
            "id": "litany",
            "word": "litany"
        },
        {
            "id": "liturgical",
            "word": "liturgical"
        },
        {
            "id": "liturgics",
            "word": "liturgics"
        },
        {
            "id": "liturgist",
            "word": "liturgist"
        },
        {
            "id": "liturgy",
            "word": "liturgy"
        },
        {
            "id": "living",
            "word": "living"
        },
        {
            "id": "local_preacher",
            "word": "local preacher"
        },
        {
            "id": "locum_tenens",
            "word": "locum tenens"
        },
        {
            "id": "lord_bishop",
            "word": "lord bishop"
        },
        {
            "id": "lord_commissioner",
            "word": "lord commissioner"
        },
        {
            "id": "lords_spiritual",
            "word": "lords spiritual"
        },
        {
            "id": "manse",
            "word": "manse"
        },
        {
            "id": "martyrology",
            "word": "martyrology"
        },
        {
            "id": "matins",
            "word": "matins"
        },
        {
            "id": "minor_canon",
            "word": "minor canon"
        },
        {
            "id": "minor_orders",
            "word": "minor orders"
        },
        {
            "id": "miserere",
            "word": "miserere"
        },
        {
            "id": "mitre",
            "word": "mitre"
        },
        {
            "id": "monastery",
            "word": "monastery"
        },
        {
            "id": "monition",
            "word": "monition"
        },
        {
            "id": "morning_service",
            "word": "morning service"
        },
        {
            "id": "most_reverend",
            "word": "most reverend"
        },
        {
            "id": "mother_house",
            "word": "mother house"
        },
        {
            "id": "movable_feast",
            "word": "movable feast"
        },
        {
            "id": "none",
            "word": "none"
        },
        {
            "id": "non-ecclesiastical",
            "word": "non-ecclesiastical"
        },
        {
            "id": "non-ordained",
            "word": "non-ordained"
        },
        {
            "id": "non_placet",
            "word": "non placet"
        },
        {
            "id": "non-secular",
            "word": "non-secular"
        },
        {
            "id": "notitia",
            "word": "notitia"
        },
        {
            "id": "novitiate",
            "word": "novitiate"
        },
        {
            "id": "nunc_dimittis",
            "word": "nunc dimittis"
        },
        {
            "id": "nunnery",
            "word": "nunnery"
        },
        {
            "id": "offertory",
            "word": "offertory"
        },
        {
            "id": "officiant",
            "word": "officiant"
        },
        {
            "id": "opus_dei",
            "word": "opus dei"
        },
        {
            "id": "ordain",
            "word": "ordain"
        },
        {
            "id": "order_of_service",
            "word": "order of service"
        },
        {
            "id": "ordinand",
            "word": "ordinand"
        },
        {
            "id": "ordination",
            "word": "ordination"
        },
        {
            "id": "orphrey",
            "word": "orphrey"
        },
        {
            "id": "pallium",
            "word": "pallium"
        },
        {
            "id": "pardoner",
            "word": "pardoner"
        },
        {
            "id": "parish",
            "word": "parish"
        },
        {
            "id": "parish_clerk",
            "word": "parish clerk"
        },
        {
            "id": "parishioner",
            "word": "parishioner"
        },
        {
            "id": "parish_register",
            "word": "parish register"
        },
        {
            "id": "parochial",
            "word": "parochial"
        },
        {
            "id": "parson",
            "word": "parson"
        },
        {
            "id": "parsonage",
            "word": "parsonage"
        },
        {
            "id": "passing_bell",
            "word": "passing bell"
        },
        {
            "id": "pastor",
            "word": "pastor"
        },
        {
            "id": "pastoral_letter",
            "word": "pastoral letter"
        },
        {
            "id": "pastoral_staff",
            "word": "pastoral staff"
        },
        {
            "id": "pastorate",
            "word": "pastorate"
        },
        {
            "id": "paten",
            "word": "paten"
        },
        {
            "id": "patriarchate",
            "word": "patriarchate"
        },
        {
            "id": "pectoral_cross",
            "word": "pectoral cross"
        },
        {
            "id": "peter%27s_pence",
            "word": "peter's pence"
        },
        {
            "id": "placet",
            "word": "placet"
        },
        {
            "id": "plain_service",
            "word": "plain service"
        },
        {
            "id": "poor_box",
            "word": "poor box"
        },
        {
            "id": "poor_clare",
            "word": "poor clare"
        },
        {
            "id": "pope",
            "word": "pope"
        },
        {
            "id": "poverty",
            "word": "poverty"
        },
        {
            "id": "praemunire",
            "word": "praemunire"
        },
        {
            "id": "preb.",
            "word": "preb."
        },
        {
            "id": "prebend",
            "word": "prebend"
        },
        {
            "id": "prebendal",
            "word": "prebendal"
        },
        {
            "id": "prebendary",
            "word": "prebendary"
        },
        {
            "id": "predikant",
            "word": "predikant"
        },
        {
            "id": "prelacy",
            "word": "prelacy"
        },
        {
            "id": "prelate",
            "word": "prelate"
        },
        {
            "id": "prelature",
            "word": "prelature"
        },
        {
            "id": "prerogative_court",
            "word": "prerogative court"
        },
        {
            "id": "presbyter",
            "word": "presbyter"
        },
        {
            "id": "presbyterianism",
            "word": "presbyterianism"
        },
        {
            "id": "presentative",
            "word": "presentative"
        },
        {
            "id": "presentee",
            "word": "presentee"
        },
        {
            "id": "priest-in-charge",
            "word": "priest-in-charge"
        },
        {
            "id": "primate",
            "word": "primate"
        },
        {
            "id": "primate_of_all_ireland",
            "word": "primate of all ireland"
        },
        {
            "id": "primate_of_england",
            "word": "primate of england"
        },
        {
            "id": "primus",
            "word": "primus"
        },
        {
            "id": "prince_of_the_church",
            "word": "prince of the church"
        },
        {
            "id": "prioress",
            "word": "prioress"
        },
        {
            "id": "priory",
            "word": "priory"
        },
        {
            "id": "processional",
            "word": "processional"
        },
        {
            "id": "prolocutor",
            "word": "prolocutor"
        },
        {
            "id": "provisor",
            "word": "provisor"
        },
        {
            "id": "reconsecrate",
            "word": "reconsecrate"
        },
        {
            "id": "rector",
            "word": "rector"
        },
        {
            "id": "rectory",
            "word": "rectory"
        },
        {
            "id": "red_hat",
            "word": "red hat"
        },
        {
            "id": "regalism",
            "word": "regalism"
        },
        {
            "id": "requiescat",
            "word": "requiescat"
        },
        {
            "id": "residentiary",
            "word": "residentiary"
        },
        {
            "id": "respond",
            "word": "respond"
        },
        {
            "id": "responsorial",
            "word": "responsorial"
        },
        {
            "id": "responsory",
            "word": "responsory"
        },
        {
            "id": "revd",
            "word": "revd"
        },
        {
            "id": "reverend",
            "word": "reverend"
        },
        {
            "id": "reverend_mother",
            "word": "reverend mother"
        },
        {
            "id": "right_reverend",
            "word": "right reverend"
        },
        {
            "id": "rochet",
            "word": "rochet"
        },
        {
            "id": "rt_revd",
            "word": "rt revd"
        },
        {
            "id": "ruling_elder",
            "word": "ruling elder"
        },
        {
            "id": "sacramental",
            "word": "sacramental"
        },
        {
            "id": "sacramentalize",
            "word": "sacramentalize"
        },
        {
            "id": "sacring",
            "word": "sacring"
        },
        {
            "id": "sacring_bell",
            "word": "sacring bell"
        },
        {
            "id": "sacristan",
            "word": "sacristan"
        },
        {
            "id": "sanctuary_lamp",
            "word": "sanctuary lamp"
        },
        {
            "id": "sanctus",
            "word": "sanctus"
        },
        {
            "id": "santon",
            "word": "santon"
        },
        {
            "id": "sarum",
            "word": "sarum"
        },
        {
            "id": "secular_arm",
            "word": "secular arm"
        },
        {
            "id": "secularize",
            "word": "secularize"
        },
        {
            "id": "sederunt",
            "word": "sederunt"
        },
        {
            "id": "see",
            "word": "see"
        },
        {
            "id": "sermon",
            "word": "sermon"
        },
        {
            "id": "sermonette",
            "word": "sermonette"
        },
        {
            "id": "service_book",
            "word": "service book"
        },
        {
            "id": "session_clerk",
            "word": "session clerk"
        },
        {
            "id": "sext",
            "word": "sext"
        },
        {
            "id": "sexton",
            "word": "sexton"
        },
        {
            "id": "shaveling",
            "word": "shaveling"
        },
        {
            "id": "sidesman",
            "word": "sidesman"
        },
        {
            "id": "simoniac",
            "word": "simoniac"
        },
        {
            "id": "simony",
            "word": "simony"
        },
        {
            "id": "sister_of_mercy",
            "word": "sister of mercy"
        },
        {
            "id": "son_%28or_daughter%29_of_the_manse",
            "word": "son (or daughter) of the manse"
        },
        {
            "id": "ss",
            "word": "ss"
        },
        {
            "id": "stipend",
            "word": "stipend"
        },
        {
            "id": "stipendiary",
            "word": "stipendiary"
        },
        {
            "id": "subdeacon",
            "word": "subdeacon"
        },
        {
            "id": "subdiaconate",
            "word": "subdiaconate"
        },
        {
            "id": "succentor",
            "word": "succentor"
        },
        {
            "id": "succursal",
            "word": "succursal"
        },
        {
            "id": "suffragan",
            "word": "suffragan"
        },
        {
            "id": "surplice",
            "word": "surplice"
        },
        {
            "id": "synod",
            "word": "synod"
        },
        {
            "id": "synodal",
            "word": "synodal"
        },
        {
            "id": "synodical",
            "word": "synodical"
        },
        {
            "id": "team_ministry",
            "word": "team ministry"
        },
        {
            "id": "temporal_power",
            "word": "temporal power"
        },
        {
            "id": "terce",
            "word": "terce"
        },
        {
            "id": "tithe",
            "word": "tithe"
        },
        {
            "id": "titular",
            "word": "titular"
        },
        {
            "id": "tonsure",
            "word": "tonsure"
        },
        {
            "id": "trent%2C_council_of",
            "word": "trent, council of"
        },
        {
            "id": "tunicle",
            "word": "tunicle"
        },
        {
            "id": "ultramontane",
            "word": "ultramontane"
        },
        {
            "id": "uncanonical",
            "word": "uncanonical"
        },
        {
            "id": "unchurch",
            "word": "unchurch"
        },
        {
            "id": "unordained",
            "word": "unordained"
        },
        {
            "id": "ven.",
            "word": "ven."
        },
        {
            "id": "venerable",
            "word": "venerable"
        },
        {
            "id": "venite",
            "word": "venite"
        },
        {
            "id": "verge",
            "word": "verge"
        },
        {
            "id": "verger",
            "word": "verger"
        },
        {
            "id": "versicle",
            "word": "versicle"
        },
        {
            "id": "very_reverend",
            "word": "very reverend"
        },
        {
            "id": "vesper",
            "word": "vesper"
        },
        {
            "id": "vestment",
            "word": "vestment"
        },
        {
            "id": "vestryman",
            "word": "vestryman"
        },
        {
            "id": "viaticum",
            "word": "viaticum"
        },
        {
            "id": "vicar",
            "word": "vicar"
        },
        {
            "id": "vicarage",
            "word": "vicarage"
        },
        {
            "id": "vicar_general",
            "word": "vicar general"
        },
        {
            "id": "vicarial",
            "word": "vicarial"
        },
        {
            "id": "vicariate",
            "word": "vicariate"
        },
        {
            "id": "voluntarism",
            "word": "voluntarism"
        },
        {
            "id": "vow",
            "word": "vow"
        },
        {
            "id": "wimple",
            "word": "wimple"
        },
        {
            "id": "zucchetto",
            "word": "zucchetto"
        }
    ],
    "metadata": {
        "limit": 5000,
        "sourceLanguage": "en",
        "total": 340,
        "provider": "Oxford University Press",
        "offset": 0
    }
}
