{
    "metadata": {
        "offset": 0,
        "limit": 5000,
        "provider": "Oxford University Press",
        "sourceLanguage": "en",
        "total": 159
    },
    "results": [
        {
            "id": "absolutize",
            "word": "absolutize"
        },
        {
            "id": "adoptionist",
            "word": "adoptionist"
        },
        {
            "id": "agape",
            "word": "agape"
        },
        {
            "id": "anabaptism",
            "word": "anabaptism"
        },
        {
            "id": "angelology",
            "word": "angelology"
        },
        {
            "id": "anthropomorphism",
            "word": "anthropomorphism"
        },
        {
            "id": "anthropomorphize",
            "word": "anthropomorphize"
        },
        {
            "id": "antinomian",
            "word": "antinomian"
        },
        {
            "id": "apologetics",
            "word": "apologetics"
        },
        {
            "id": "apophatic",
            "word": "apophatic"
        },
        {
            "id": "arch-fiend",
            "word": "arch-fiend"
        },
        {
            "id": "argument_from_design",
            "word": "argument from design"
        },
        {
            "id": "arianism",
            "word": "arianism"
        },
        {
            "id": "asceticism",
            "word": "asceticism"
        },
        {
            "id": "atonement",
            "word": "atonement"
        },
        {
            "id": "augsburg_confession",
            "word": "augsburg confession"
        },
        {
            "id": "cardinal_sin",
            "word": "cardinal sin"
        },
        {
            "id": "cardinal_virtue",
            "word": "cardinal virtue"
        },
        {
            "id": "cataphatic",
            "word": "cataphatic"
        },
        {
            "id": "catechetics",
            "word": "catechetics"
        },
        {
            "id": "charism",
            "word": "charism"
        },
        {
            "id": "christology",
            "word": "christology"
        },
        {
            "id": "church_militant",
            "word": "church militant"
        },
        {
            "id": "concomitance",
            "word": "concomitance"
        },
        {
            "id": "consubstantial",
            "word": "consubstantial"
        },
        {
            "id": "consubstantiation",
            "word": "consubstantiation"
        },
        {
            "id": "covenant_of_grace",
            "word": "covenant of grace"
        },
        {
            "id": "covenant_of_works",
            "word": "covenant of works"
        },
        {
            "id": "dark_night_of_the_soul",
            "word": "dark night of the soul"
        },
        {
            "id": "deism",
            "word": "deism"
        },
        {
            "id": "demythologize",
            "word": "demythologize"
        },
        {
            "id": "depravity",
            "word": "depravity"
        },
        {
            "id": "devil",
            "word": "devil"
        },
        {
            "id": "discarnate",
            "word": "discarnate"
        },
        {
            "id": "dispensationalism",
            "word": "dispensationalism"
        },
        {
            "id": "dissent",
            "word": "dissent"
        },
        {
            "id": "eschatological",
            "word": "eschatological"
        },
        {
            "id": "eschatology",
            "word": "eschatology"
        },
        {
            "id": "eternal_life",
            "word": "eternal life"
        },
        {
            "id": "exegesis",
            "word": "exegesis"
        },
        {
            "id": "exegete",
            "word": "exegete"
        },
        {
            "id": "fallen_angel",
            "word": "fallen angel"
        },
        {
            "id": "felix_culpa",
            "word": "felix culpa"
        },
        {
            "id": "first_cause",
            "word": "first cause"
        },
        {
            "id": "form_criticism",
            "word": "form criticism"
        },
        {
            "id": "free_will",
            "word": "free will"
        },
        {
            "id": "heresiarch",
            "word": "heresiarch"
        },
        {
            "id": "higher_criticism",
            "word": "higher criticism"
        },
        {
            "id": "holy_spirit",
            "word": "holy spirit"
        },
        {
            "id": "homoiousian",
            "word": "homoiousian"
        },
        {
            "id": "homoousian",
            "word": "homoousian"
        },
        {
            "id": "hylic",
            "word": "hylic"
        },
        {
            "id": "hypostatic",
            "word": "hypostatic"
        },
        {
            "id": "hypostatic_union",
            "word": "hypostatic union"
        },
        {
            "id": "impanation",
            "word": "impanation"
        },
        {
            "id": "impassible",
            "word": "impassible"
        },
        {
            "id": "impeccable",
            "word": "impeccable"
        },
        {
            "id": "impute",
            "word": "impute"
        },
        {
            "id": "infralapsarian",
            "word": "infralapsarian"
        },
        {
            "id": "intercommunion",
            "word": "intercommunion"
        },
        {
            "id": "isagogics",
            "word": "isagogics"
        },
        {
            "id": "kairos",
            "word": "kairos"
        },
        {
            "id": "kenosis",
            "word": "kenosis"
        },
        {
            "id": "kerygma",
            "word": "kerygma"
        },
        {
            "id": "latria",
            "word": "latria"
        },
        {
            "id": "legalism",
            "word": "legalism"
        },
        {
            "id": "legalistic",
            "word": "legalistic"
        },
        {
            "id": "liberation_theology",
            "word": "liberation theology"
        },
        {
            "id": "logion",
            "word": "logion"
        },
        {
            "id": "logos",
            "word": "logos"
        },
        {
            "id": "lutheran",
            "word": "lutheran"
        },
        {
            "id": "marcan",
            "word": "marcan"
        },
        {
            "id": "mariology",
            "word": "mariology"
        },
        {
            "id": "means_of_grace",
            "word": "means of grace"
        },
        {
            "id": "millenarian",
            "word": "millenarian"
        },
        {
            "id": "modalism",
            "word": "modalism"
        },
        {
            "id": "monism",
            "word": "monism"
        },
        {
            "id": "monotheism",
            "word": "monotheism"
        },
        {
            "id": "monotheistic",
            "word": "monotheistic"
        },
        {
            "id": "moral_theology",
            "word": "moral theology"
        },
        {
            "id": "natural_theology",
            "word": "natural theology"
        },
        {
            "id": "natural_virtues",
            "word": "natural virtues"
        },
        {
            "id": "nestorianism",
            "word": "nestorianism"
        },
        {
            "id": "new_covenant",
            "word": "new covenant"
        },
        {
            "id": "old_covenant",
            "word": "old covenant"
        },
        {
            "id": "panentheism",
            "word": "panentheism"
        },
        {
            "id": "paraclete",
            "word": "paraclete"
        },
        {
            "id": "passible",
            "word": "passible"
        },
        {
            "id": "pastoral_theology",
            "word": "pastoral theology"
        },
        {
            "id": "patristic",
            "word": "patristic"
        },
        {
            "id": "patristics",
            "word": "patristics"
        },
        {
            "id": "pericope",
            "word": "pericope"
        },
        {
            "id": "pleroma",
            "word": "pleroma"
        },
        {
            "id": "pneumatology",
            "word": "pneumatology"
        },
        {
            "id": "postlapsarian",
            "word": "postlapsarian"
        },
        {
            "id": "predestinate",
            "word": "predestinate"
        },
        {
            "id": "predestination",
            "word": "predestination"
        },
        {
            "id": "predestine",
            "word": "predestine"
        },
        {
            "id": "predetermine",
            "word": "predetermine"
        },
        {
            "id": "prelapsarian",
            "word": "prelapsarian"
        },
        {
            "id": "premillennialism",
            "word": "premillennialism"
        },
        {
            "id": "profane",
            "word": "profane"
        },
        {
            "id": "quodlibet",
            "word": "quodlibet"
        },
        {
            "id": "rationalism",
            "word": "rationalism"
        },
        {
            "id": "rationalist",
            "word": "rationalist"
        },
        {
            "id": "real_presence",
            "word": "real presence"
        },
        {
            "id": "remissible",
            "word": "remissible"
        },
        {
            "id": "remit",
            "word": "remit"
        },
        {
            "id": "remonstrance",
            "word": "remonstrance"
        },
        {
            "id": "rigorism",
            "word": "rigorism"
        },
        {
            "id": "sabellian",
            "word": "sabellian"
        },
        {
            "id": "salvation",
            "word": "salvation"
        },
        {
            "id": "salvific",
            "word": "salvific"
        },
        {
            "id": "scholasticism",
            "word": "scholasticism"
        },
        {
            "id": "second_coming",
            "word": "second coming"
        },
        {
            "id": "see_the_light",
            "word": "see the light"
        },
        {
            "id": "semi-pelagian",
            "word": "semi-pelagian"
        },
        {
            "id": "seraph",
            "word": "seraph"
        },
        {
            "id": "sortes",
            "word": "sortes"
        },
        {
            "id": "soteriology",
            "word": "soteriology"
        },
        {
            "id": "source_criticism",
            "word": "source criticism"
        },
        {
            "id": "state_of_grace",
            "word": "state of grace"
        },
        {
            "id": "systematic_theology",
            "word": "systematic theology"
        },
        {
            "id": "tempter",
            "word": "tempter"
        },
        {
            "id": "textual_criticism",
            "word": "textual criticism"
        },
        {
            "id": "theanthropic",
            "word": "theanthropic"
        },
        {
            "id": "theism",
            "word": "theism"
        },
        {
            "id": "theistic",
            "word": "theistic"
        },
        {
            "id": "theocentric",
            "word": "theocentric"
        },
        {
            "id": "theodicy",
            "word": "theodicy"
        },
        {
            "id": "theologian",
            "word": "theologian"
        },
        {
            "id": "theological",
            "word": "theological"
        },
        {
            "id": "theologically",
            "word": "theologically"
        },
        {
            "id": "theological_virtues",
            "word": "theological virtues"
        },
        {
            "id": "theologize",
            "word": "theologize"
        },
        {
            "id": "theology",
            "word": "theology"
        },
        {
            "id": "theophany",
            "word": "theophany"
        },
        {
            "id": "theophoric",
            "word": "theophoric"
        },
        {
            "id": "thomism",
            "word": "thomism"
        },
        {
            "id": "thought_form",
            "word": "thought form"
        },
        {
            "id": "total_depravity",
            "word": "total depravity"
        },
        {
            "id": "traditionalism",
            "word": "traditionalism"
        },
        {
            "id": "transubstantiate",
            "word": "transubstantiate"
        },
        {
            "id": "transubstantiation",
            "word": "transubstantiation"
        },
        {
            "id": "trichotomy",
            "word": "trichotomy"
        },
        {
            "id": "trinity",
            "word": "trinity"
        },
        {
            "id": "tritheism",
            "word": "tritheism"
        },
        {
            "id": "triune",
            "word": "triune"
        },
        {
            "id": "ubiquitarian",
            "word": "ubiquitarian"
        },
        {
            "id": "unitarian",
            "word": "unitarian"
        },
        {
            "id": "universalism",
            "word": "universalism"
        },
        {
            "id": "universalist",
            "word": "universalist"
        },
        {
            "id": "unregenerate",
            "word": "unregenerate"
        },
        {
            "id": "unscriptural",
            "word": "unscriptural"
        },
        {
            "id": "venial",
            "word": "venial"
        },
        {
            "id": "via_negativa",
            "word": "via negativa"
        },
        {
            "id": "virgin_birth",
            "word": "virgin birth"
        },
        {
            "id": "yahweh",
            "word": "yahweh"
        },
        {
            "id": "yahwist",
            "word": "yahwist"
        }
    ]
}
